sagea/__init__.py
sagea/_version.py
sagea/__data__/Geometric/PHISFC_ERA5_invariant.nc
sagea/__data__/LoveNumber/LoveNumber.mat
sagea/__data__/auxiliary/GIF48.gfc
sagea/__data__/auxiliary/ocean360_grndline.sh
sagea/pysrc/__init__.py
sagea/pysrc/auxiliary/FileTool.py
sagea/pysrc/auxiliary/LoveNumber.py
sagea/pysrc/auxiliary/MathTool.py
sagea/pysrc/auxiliary/Preference.py
sagea/pysrc/auxiliary/TimeTool.py
sagea/pysrc/auxiliary/__init__.py
sagea/pysrc/data_class/__GRD__.py
sagea/pysrc/data_class/__SHC__.py
sagea/pysrc/data_class/__SHCov__.py
sagea/pysrc/data_class/__init__.py
sagea/pysrc/data_collection/__init__.py
sagea/pysrc/data_collection/collect_auxiliary.py
sagea/pysrc/data_collection/processing_bar.py
sagea/pysrc/error_assessment/__init__.py
sagea/pysrc/error_assessment/tch/TCH.py
sagea/pysrc/error_assessment/tch/__init__.py
sagea/pysrc/load_file/LoadCov.py
sagea/pysrc/load_file/LoadL2LowDeg.py
sagea/pysrc/load_file/LoadL2SH.py
sagea/pysrc/load_file/LoadNoah.py
sagea/pysrc/load_file/LoadSHP.py
sagea/pysrc/load_file/LoadShpOld.py
sagea/pysrc/load_file/__init__.py
sagea/pysrc/load_file/loadGFC.py
sagea/pysrc/post_processing/__init__.py
sagea/pysrc/post_processing/GAX_correction/GAXCorrection.py
sagea/pysrc/post_processing/GAX_correction/__init__.py
sagea/pysrc/post_processing/GIA_correction/GIACorrectionSpectral.py
sagea/pysrc/post_processing/GIA_correction/__init__.py
sagea/pysrc/post_processing/GMAMCorrection/GMAMCorrection.py
sagea/pysrc/post_processing/GMAMCorrection/__init__.py
sagea/pysrc/post_processing/convert_field_physical_quantity/ConvertSHC.py
sagea/pysrc/post_processing/convert_field_physical_quantity/__init__.py
sagea/pysrc/post_processing/de_aliasing/DeAliasing.py
sagea/pysrc/post_processing/de_aliasing/__init__.py
sagea/pysrc/post_processing/extract_basin_signal/ExtractSpatialSignal.py
sagea/pysrc/post_processing/extract_basin_signal/ExtractSpatialSignalConfig.py
sagea/pysrc/post_processing/extract_basin_signal/ExtractSpectralSignal.py
sagea-0.2.3a1.dist-info/LICENSE
sagea-0.2.3a1.dist-info/METADATA
sagea-0.2.3a1.dist-info/WHEEL
sagea-0.2.3a1.dist-info/top_level.txt
sagea-0.2.3a1.dist-info/RECORD
