Metadata-Version: 2.1
Name: sagea
Version: 0.2.3a1
Summary: satellite gravity post-processing and error assessment
Home-page: https://github.com/LiuSH1997/sageaPyPI
Author: Shuhao Liu
Author-email: liushuhao@hust.edu.cn
License: MIT
Classifier: License :: OSI Approved :: MIT License
Classifier: Programming Language :: Python
Classifier: Programming Language :: Python :: 3
Classifier: Programming Language :: Python :: 3.6
Classifier: Programming Language :: Python :: Implementation :: CPython
Classifier: Programming Language :: Python :: Implementation :: PyPy
Requires-Python: >=3.9.0
License-File: LICENSE
Requires-Dist: numpy (==2.0.2)
Requires-Dist: scipy (==1.13.1)
Requires-Dist: h5py (==3.14.0)
Requires-Dist: pandas (==2.3.0)
Requires-Dist: tqdm (==4.67.1)
Requires-Dist: netCDF4 (==1.7.2)
Requires-Dist: geopandas (==1.0.1)
Requires-Dist: shapely (==2.0.7)
Requires-Dist: pyproj (==3.6.1)
Requires-Dist: rasterio (==1.4.3)
Requires-Dist: cartopy (==0.23.0)
Requires-Dist: wget (==3.2)
